Metadata-Version: 2.1
Name: Kigo
Version: 0.0.8
Summary: Python framework for Event Async RPC
Home-page: https://github.com/AsyncMicroStack/kigo
Author: Krzysztof Kaczkowski
Author-email: krzysztof.kaczkowski@architekt-it.pl
License: UNKNOWN
Platform: UNKNOWN
Classifier: Development Status :: 1 - Planning
Classifier: Programming Language :: Python :: 3.8
Classifier: License :: OSI Approved :: Apache Software License
Classifier: Operating System :: OS Independent
Requires-Python: >=3.8
Provides-Extra: docs
